{
    "Ar36": {
        "error": 0.00020018786592900613,
        "error_type": "",
        "fit": "previous",
        "references": [
            {
                "exclude": false,
                "record_id": "ba-01-A-2441"
            }
        ],
        "value": 0.004938624008135686
    },
    "Ar36L2": {
        "error": 0.008411954667689524,
        "error_type": "",
        "fit": "previous",
        "references": [
            {
                "exclude": false,
                "record_id": "ba-01-A-2441"
            }
        ],
        "value": 0.0018887865526327138
    },
    "Ar37": {
        "error": 0.007569812646866102,
        "error_type": "",
        "fit": "previous",
        "references": [
            {
                "exclude": false,
                "record_id": "ba-01-A-2441"
            }
        ],
        "value": 0.023738259570521485
    },
    "Ar37L1": {
        "error": 0.019872312930775363,
        "error_type": "",
        "fit": "previous",
        "references": [
            {
                "exclude": false,
                "record_id": "ba-01-A-2441"
            }
        ],
        "value": 0.05125588111203316
    },
    "Ar38": {
        "error": 0.018602229974108788,
        "error_type": "",
        "fit": "previous",
        "references": [
            {
                "exclude": false,
                "record_id": "ba-01-A-2441"
            }
        ],
        "value": 0.009436145381056832
    },
    "Ar38AX": {
        "error": 0.007383467999177914,
        "error_type": "",
        "fit": "previous",
        "references": [
            {
                "exclude": false,
                "record_id": "ba-01-A-2441"
            }
        ],
        "value": 0.0012557875065297222
    },
    "Ar39": {
        "error": 0.007467220766397754,
        "error_type": "",
        "fit": "previous",
        "references": [
            {
                "exclude": false,
                "record_id": "ba-01-A-2441"
            }
        ],
        "value": 0.006602307373415394
    },
    "Ar39H1": {
        "error": 0.01686919978246459,
        "error_type": "",
        "fit": "previous",
        "references": [
            {
                "exclude": false,
                "record_id": "ba-01-A-2441"
            }
        ],
        "value": 0.019924821785006985
    },
    "Ar40": {
        "error": 0.028096993052047783,
        "error_type": "",
        "fit": "previous",
        "references": [
            {
                "exclude": false,
                "record_id": "ba-01-A-2441"
            }
        ],
        "value": 1.0752424090362311
    },
    "Ar40H2": {
        "error": 0.02294673072989549,
        "error_type": "",
        "fit": "previous",
        "references": [
            {
                "exclude": false,
                "record_id": "ba-01-A-2441"
            }
        ],
        "value": 1.023475677066147
    },
    "Ar41": {
        "error": 0.0,
        "error_type": "",
        "fit": "previous",
        "references": [
            {
                "exclude": false,
                "record_id": "ba-01-A-2441"
            }
        ],
        "value": 0.09231696766878858
    }
}