{
    "Ar36": {
        "error": 0.00022886921264899505,
        "error_type": "",
        "fit": "previous",
        "references": [
            {
                "exclude": false,
                "record_id": "ba-01-A-2235"
            }
        ],
        "value": 0.0054196223460911495
    },
    "Ar36L2": {
        "error": 0.0075554607382938505,
        "error_type": "",
        "fit": "previous",
        "references": [
            {
                "exclude": false,
                "record_id": "ba-01-A-2235"
            }
        ],
        "value": -0.011145115282751646
    },
    "Ar37": {
        "error": 0.008290312921153599,
        "error_type": "",
        "fit": "previous",
        "references": [
            {
                "exclude": false,
                "record_id": "ba-01-A-2235"
            }
        ],
        "value": 0.03351441322988037
    },
    "Ar37L1": {
        "error": 0.017621503522280133,
        "error_type": "",
        "fit": "previous",
        "references": [
            {
                "exclude": false,
                "record_id": "ba-01-A-2235"
            }
        ],
        "value": 0.059643770783258304
    },
    "Ar38": {
        "error": 0.015266536130189063,
        "error_type": "",
        "fit": "previous",
        "references": [
            {
                "exclude": false,
                "record_id": "ba-01-A-2235"
            }
        ],
        "value": 0.03367617706087844
    },
    "Ar38AX": {
        "error": 0.007782214472354444,
        "error_type": "",
        "fit": "previous",
        "references": [
            {
                "exclude": false,
                "record_id": "ba-01-A-2235"
            }
        ],
        "value": 0.005442717050915827
    },
    "Ar39": {
        "error": 0.009910574878292623,
        "error_type": "",
        "fit": "previous",
        "references": [
            {
                "exclude": false,
                "record_id": "ba-01-A-2235"
            }
        ],
        "value": 0.09316059257238722
    },
    "Ar39H1": {
        "error": 0.016289777150865433,
        "error_type": "",
        "fit": "previous",
        "references": [
            {
                "exclude": false,
                "record_id": "ba-01-A-2235"
            }
        ],
        "value": 0.05592491704298447
    },
    "Ar40": {
        "error": 0.029919683877255306,
        "error_type": "",
        "fit": "previous",
        "references": [
            {
                "exclude": false,
                "record_id": "ba-01-A-2235"
            }
        ],
        "value": 0.9947900694957797
    },
    "Ar40H2": {
        "error": 0.025574782460215016,
        "error_type": "",
        "fit": "previous",
        "references": [
            {
                "exclude": false,
                "record_id": "ba-01-A-2235"
            }
        ],
        "value": 1.071007805414663
    },
    "Ar41": {
        "error": 0.0,
        "error_type": "",
        "fit": "previous",
        "references": [
            {
                "exclude": false,
                "record_id": "ba-01-A-2235"
            }
        ],
        "value": 0.08654386540404418
    }
}