{
    "Ar36": {
        "error": 0.00022935144346596082,
        "error_type": "",
        "fit": "previous",
        "references": [
            {
                "exclude": false,
                "record_id": "ba-01-A-2287"
            }
        ],
        "value": 0.006374650054514819
    },
    "Ar36L2": {
        "error": 0.0073192685435667605,
        "error_type": "",
        "fit": "previous",
        "references": [
            {
                "exclude": false,
                "record_id": "ba-01-A-2287"
            }
        ],
        "value": 0.013577177425459188
    },
    "Ar37": {
        "error": 0.007645632794046177,
        "error_type": "",
        "fit": "previous",
        "references": [
            {
                "exclude": false,
                "record_id": "ba-01-A-2287"
            }
        ],
        "value": 0.049770408190296184
    },
    "Ar37L1": {
        "error": 0.017662718032275034,
        "error_type": "",
        "fit": "previous",
        "references": [
            {
                "exclude": false,
                "record_id": "ba-01-A-2287"
            }
        ],
        "value": 0.05215183071911955
    },
    "Ar38": {
        "error": 0.01736966243560774,
        "error_type": "",
        "fit": "previous",
        "references": [
            {
                "exclude": false,
                "record_id": "ba-01-A-2287"
            }
        ],
        "value": 0.04560202768731188
    },
    "Ar38AX": {
        "error": 0.006946572152765236,
        "error_type": "",
        "fit": "previous",
        "references": [
            {
                "exclude": false,
                "record_id": "ba-01-A-2287"
            }
        ],
        "value": -0.005120474120797456
    },
    "Ar39": {
        "error": 0.007579011358393561,
        "error_type": "",
        "fit": "previous",
        "references": [
            {
                "exclude": false,
                "record_id": "ba-01-A-2287"
            }
        ],
        "value": 0.10004883953260565
    },
    "Ar39H1": {
        "error": 0.015787080468222203,
        "error_type": "",
        "fit": "previous",
        "references": [
            {
                "exclude": false,
                "record_id": "ba-01-A-2287"
            }
        ],
        "value": 0.12360932049603277
    },
    "Ar40": {
        "error": 0.03029060317493573,
        "error_type": "",
        "fit": "previous",
        "references": [
            {
                "exclude": false,
                "record_id": "ba-01-A-2287"
            }
        ],
        "value": 1.9286227852567706
    },
    "Ar40H2": {
        "error": 0.024816974096185176,
        "error_type": "",
        "fit": "previous",
        "references": [
            {
                "exclude": false,
                "record_id": "ba-01-A-2287"
            }
        ],
        "value": 1.8359408085591034
    },
    "Ar41": {
        "error": 0.0,
        "error_type": "",
        "fit": "previous",
        "references": [
            {
                "exclude": false,
                "record_id": "ba-01-A-2287"
            }
        ],
        "value": 0.05836147134525015
    }
}